python_version.py
pyvm_tui.py
pyvm_updater-2.1.0.dist-info/licenses/LICENSE
pyvm_updater-2.1.0.dist-info/METADATA
pyvm_updater-2.1.0.dist-info/WHEEL
pyvm_updater-2.1.0.dist-info/entry_points.txt
pyvm_updater-2.1.0.dist-info/top_level.txt
pyvm_updater-2.1.0.dist-info/RECORD
